{
  "parserType": "Glob",
  "configTitle": "Adobe Flash - Ruffle",
  "steamCategory": "${Flash}",
  "steamDirectory": "${steamdirglobal}",
  "romDirectory": "${romsdirglobal}/flash",
  "executableArgs": " \"${fileName}\"",
  "executableModifier": "\"${exePath}\"",
  "startInDirectory": "",
  "titleModifier": "${fuzzyTitle}",
  "imageProviders": ["SteamGridDB"],
  "onlineImageQueries": "${${fuzzyTitle}}",
  "imagePool": "${fuzzyTitle}",
  "defaultImage": "",
  "defaultTallImage": "",
  "defaultHeroImage": "",
  "defaultLogoImage": "",
  "defaultIcon": "/home/deck/.config/EmuDeck/backend/configs/steam-rom-manager/userData/img/default/icon.png",
  "localImages": "",
  "localTallImages": "",
  "localHeroImages": "",
  "localLogoImages": "",
  "localIcons": "",
  "userAccounts": {
    "specifiedAccounts": "",
    "skipWithMissingDataDir": true,
    "useCredentials": true
  },
  "executable": {
    "path": "/run/media/mmcblk0p1/Emulation/tools/launchers/ruffle.sh",
    "shortcutPassthrough": false,
    "appendArgsToExecutable": true
  },
  "parserInputs": {
    "glob": "${title}@(.swf|.SWF)"
  },
  "titleFromVariable": {
    "limitToGroups": "",
    "caseInsensitiveVariables": false,
    "skipFileIfVariableWasNotFound": false,
    "tryToMatchTitle": true
  },
  "fuzzyMatch": {
    "replaceDiacritics": true,
    "removeCharacters": true,
    "removeBrackets": true
  },
  "imageProviderAPIs": {
    "SteamGridDB": {
      "nsfw": false,
      "humor": false,
      "styles": [],
      "stylesHero": [],
      "stylesLogo": [],
      "stylesIcon": [],
      "imageMotionTypes": ["static"]
    }
  },
  "parserId": "165964954316677676",
  "version": 1
}
